02.multiplexer/00.basic/multiplexer.v
// 4 in 1 multiplexer
module multiplexer (
    input i0, i1, i2, i3,
    output out,
    input s0, s1
);

wire y0, y1, y2, y3;
wire s0n, s1n;

not n1(s0n, s0);
not n2(s1n, s1);

and a1(y0, i0, s1n, s0n);
and a2(y1, i1, s1n, s0);
and a3(y2, i2, s1, s0n);
and a4(y3, i3, s1, s0);

or o(out, y0, y1, y2, y3);

endmodule

02.multiplexer/02.ternary operator/mux_tb.v
module top;

reg i0, i1, i2, i3;
wire out;
reg s0, s1;

multiplexer m1(.i0(i0), .i1(i1), .i2(i2), .i3(i3), .out(out), .s0(s0), .s1(s1));

initial begin
    $dumpfile("muxgen.vcd");
    $dumpvars(0, m1);
end

initial begin
    s0 = 0; s1 = 0; i0 = 1; i1 = 0; i2 = 0; i3 = 0;
    $monitor($time, " s0 = %b, s1 = %b, OUT = %b", s0, s1, out);
    #1
    s0 = 1; s1 = 0;
    #1
    i0 = 0; i1 = 1;
    #1
    s0 = 0; s1 = 1;
    #1
    i1 = 0; i2 = 1;
    #1
    s0 = 1; s1 = 1;
    #1
    i2 = 0; i3 = 1;
    #1
    s0 = 0; s1 = 0;
    #1
    i3 = 0; i1 = 1;

end

endmodule

02.multiplexer/muxgen.vcd
$date
	Thu Dec 16 13:08:58 2021
$end
$version
	Icarus Verilog
$end
$timescale
	1s
$end
$scope module top $end
$scope module m1 $end
$var wire 1 ! i0 $end
$var wire 1 " i1 $end
$var wire 1 # i2 $end
$var wire 1 $ i3 $end
$var wire 1 % out $end
$var wire 1 & s0 $end
$var wire 1 ' s0n $end
$var wire 1 ( s1 $end
$var wire 1 ) s1n $end
$var wire 1 * y0 $end
$var wire 1 + y1 $end
$var wire 1 , y2 $end
$var wire 1 - y3 $end
$upscope $end
$upscope $end
$enddefinitions $end
#0
$dumpvars
0-
0,
0+
1*
1)
0(
1'
0&
1%
0$
0#
0"
1!
$end
#1
0%
0*
0'
1&
#2
1%
1+
1"
0!
#3
0%
0)
1'
0+
1(
0&
#4
1%
1,
1#
0"
#5
0%
0,
0'
1&
#6
1)
1'
0(
0&
#7
1%
1*
1!
