05.UART/uart_tx.v
//////////////////////////////////////////////////////////////////////
// Author: Russell Merrick
//////////////////////////////////////////////////////////////////////
// This file contains the UART Transmitter.  This transmitter is able
// to transmit 8 bits of serial data, one start bit, one stop bit,
// and no parity bit.  When transmit is complete o_Tx_done will be
// driven high for one clock cycle.
//
// Set Parameter CLKS_PER_BIT as follows:
// CLKS_PER_BIT = (Frequency of i_Clock)/(Frequency of UART)
// Example: 25 MHz Clock, 115200 baud UART
// (25000000)/(115200) = 217
 
module UART_TX 
  #(parameter CLKS_PER_BIT = 217)
  (
   input       i_Rst_L,
   input       i_Clock,
   input       i_TX_DV,         //TX Data Valid for one cycle
   input [7:0] i_TX_Byte, 
   output reg  o_TX_Active,
   output reg  o_TX_Serial,
   output reg  o_TX_Done
   );
 
  localparam IDLE         = 3'b000;
  localparam TX_START_BIT = 3'b001;
  localparam TX_DATA_BITS = 3'b010;
  localparam TX_STOP_BIT  = 3'b011;
  localparam CLEANUP      = 3'b100;
  
  reg [2:0] r_SM_Main;
  reg [$clog2(CLKS_PER_BIT):0] r_Clock_Count;
  reg [2:0] r_Bit_Index;
  reg [7:0] r_TX_Data;


  // Purpose: Control TX state machine
  always @(posedge i_Clock or negedge i_Rst_L)
  begin
    if (~i_Rst_L)
    begin
      r_SM_Main <= 3'b000;
      o_TX_Done <= 1'b0;
    end
    else
    begin
      case (r_SM_Main)
      IDLE :
        begin
          o_TX_Serial   <= 1'b1;         // Drive Line High for Idle
          o_TX_Done     <= 1'b0;
          r_Clock_Count <= 0;
          r_Bit_Index   <= 0;
          
          if (i_TX_DV == 1'b1)
          begin
            o_TX_Active <= 1'b1;
            r_TX_Data   <= i_TX_Byte;
            r_SM_Main   <= TX_START_BIT;
          end
          else
            r_SM_Main <= IDLE;
        end // case: IDLE
      
      
      // Send out Start Bit. Start bit = 0
      TX_START_BIT :
        begin
          o_TX_Serial <= 1'b0;
          
          // Wait CLKS_PER_BIT-1 clock cycles for start bit to finish
          if (r_Clock_Count < CLKS_PER_BIT-1)
          begin
            r_Clock_Count <= r_Clock_Count + 1;
            r_SM_Main     <= TX_START_BIT;
          end
          else
          begin
            r_Clock_Count <= 0;
            r_SM_Main     <= TX_DATA_BITS;
          end
        end // case: TX_START_BIT
      
      
      // Wait CLKS_PER_BIT-1 clock cycles for data bits to finish         
      TX_DATA_BITS :
        begin
          o_TX_Serial <= r_TX_Data[r_Bit_Index];
          
          if (r_Clock_Count < CLKS_PER_BIT-1)
          begin
            r_Clock_Count <= r_Clock_Count + 1;
            r_SM_Main     <= TX_DATA_BITS;
          end
          else
          begin
            r_Clock_Count <= 0;
            
            // Check if we have sent out all bits
            if (r_Bit_Index < 7)
            begin
              r_Bit_Index <= r_Bit_Index + 1;
              r_SM_Main   <= TX_DATA_BITS;
            end
            else
            begin
              r_Bit_Index <= 0;
              r_SM_Main   <= TX_STOP_BIT;
            end
          end 
        end // case: TX_DATA_BITS
      
      
      // Send out Stop bit.  Stop bit = 1
      TX_STOP_BIT :
        begin
          o_TX_Serial <= 1'b1;
          
          // Wait CLKS_PER_BIT-1 clock cycles for Stop bit to finish
          if (r_Clock_Count < CLKS_PER_BIT-1)
          begin
            r_Clock_Count <= r_Clock_Count + 1;
            r_SM_Main     <= TX_STOP_BIT;
          end
          else
          begin
            o_TX_Done     <= 1'b1;
            r_Clock_Count <= 0;
            r_SM_Main     <= CLEANUP;
            o_TX_Active   <= 1'b0;
          end 
        end // case: TX_STOP_BIT
      
      
      // Stay here 1 clock
      CLEANUP :
        begin
          r_SM_Main <= IDLE;
        end
      
      
      default :
        r_SM_Main <= IDLE;
      
    endcase
    end // else: !if(~i_Rst_L)
  end // always @ (posedge i_Clock or negedge i_Rst_L)

  
endmodule

05.UART/uart_rx.v
//////////////////////////////////////////////////////////////////////
// Author:      Russell Merrick
//////////////////////////////////////////////////////////////////////
// Description: This file contains the UART Receiver.  This receiver is 
//              able to receive 8 bits of serial data, one start bit, one 
//              stop bit, and no parity bit.  When receive is complete 
//              o_RX_DV will be driven high for one clock cycle.
// 
// Parameters:  Set Parameter CLKS_PER_BIT as follows:
//              CLKS_PER_BIT = (Frequency of i_Clock)/(Frequency of UART)
//              Example: 25 MHz Clock, 115200 baud UART
//              (25000000)/(115200) = 217
//////////////////////////////////////////////////////////////////////////////

module UART_RX
  #(parameter CLKS_PER_BIT = 217)
  (
   input            i_Rst_L,
   input            i_Clock,
   input            i_RX_Serial,
   output reg       o_RX_DV,        //RX Data Valid for one cycle
   output reg [7:0] o_RX_Byte
   );
   
  localparam IDLE         = 3'b000;
  localparam RX_START_BIT = 3'b001;
  localparam RX_DATA_BITS = 3'b010;
  localparam RX_STOP_BIT  = 3'b011;
  localparam CLEANUP      = 3'b100;
  
  reg [$clog2(CLKS_PER_BIT)-1:0] r_Clock_Count;
  reg [2:0] r_Bit_Index; //8 bits total
  reg [2:0] r_SM_Main;
  
  
  // Purpose: Control RX state machine
  always @(posedge i_Clock or negedge i_Rst_L)
  begin
    if (~i_Rst_L)
    begin
      r_SM_Main <= 3'b000;
      o_RX_DV   <= 1'b0;
    end
    else
    begin
      case (r_SM_Main)
      IDLE :
        begin
          o_RX_DV       <= 1'b0;
          r_Clock_Count <= 0;
          r_Bit_Index   <= 0;
          
          if (i_RX_Serial == 1'b0)          // Start bit detected
            r_SM_Main <= RX_START_BIT;
          else
            r_SM_Main <= IDLE;
        end
      
      // Check middle of start bit to make sure it's still low
      RX_START_BIT :
        begin
          if (r_Clock_Count == (CLKS_PER_BIT-1)/2)
          begin
            if (i_RX_Serial == 1'b0)
            begin
              r_Clock_Count <= 0;  // reset counter, found the middle
              r_SM_Main     <= RX_DATA_BITS;
            end
            else
              r_SM_Main <= IDLE;
          end
          else
          begin
            r_Clock_Count <= r_Clock_Count + 1;
            r_SM_Main     <= RX_START_BIT;
          end
        end // case: RX_START_BIT
      
      
      // Wait CLKS_PER_BIT-1 clock cycles to sample serial data
      RX_DATA_BITS :
        begin
          if (r_Clock_Count < CLKS_PER_BIT-1)
          begin
            r_Clock_Count <= r_Clock_Count + 1;
            r_SM_Main     <= RX_DATA_BITS;
          end
          else
          begin
            r_Clock_Count          <= 0;
            o_RX_Byte[r_Bit_Index] <= i_RX_Serial;
            
            // Check if we have received all bits
            if (r_Bit_Index < 7)
            begin
              r_Bit_Index <= r_Bit_Index + 1;
              r_SM_Main   <= RX_DATA_BITS;
            end
            else
            begin
              r_Bit_Index <= 0;
              r_SM_Main   <= RX_STOP_BIT;
            end
          end
        end // case: RX_DATA_BITS
      
      
      // Receive Stop bit.  Stop bit = 1
      RX_STOP_BIT :
        begin
          // Wait CLKS_PER_BIT-1 clock cycles for Stop bit to finish
          if (r_Clock_Count < CLKS_PER_BIT-1)
          begin
            r_Clock_Count <= r_Clock_Count + 1;
            r_SM_Main     <= RX_STOP_BIT;
          end
          else
          begin
            o_RX_DV       <= 1'b1;
            r_Clock_Count <= 0;
            r_SM_Main     <= CLEANUP;
          end
        end // case: RX_STOP_BIT
      
      
      // Stay here 1 clock
      CLEANUP :
        begin
          r_SM_Main <= IDLE;
          o_RX_DV   <= 1'b0;
        end
      
      
      default :
        r_SM_Main <= IDLE;
      
    endcase
    end // else: !if(~i_Rst_L)
  end // always @ (posedge i_Clock or negedge i_Rst_L)
  
endmodule // UART_RX

05.UART/uart_tb.v
//////////////////////////////////////////////////////////////////////
// File Downloaded from http://www.nandland.com
//////////////////////////////////////////////////////////////////////

// This testbench will exercise the UART RX.
// It sends out byte 0x37, and ensures the RX receives it correctly.
`timescale 1ns/10ps

module UART_TB ();

  // Testbench uses a 25 MHz clock
  // Want to interface to 115200 baud UART
  // 25000000 / 115200 = 217 Clocks Per Bit.
  parameter c_CLOCK_PERIOD_NS = 40;
  parameter c_CLKS_PER_BIT    = 217;
  parameter c_BIT_PERIOD      = 8600;
  
  reg r_Clock = 0;
  reg r_TX_DV = 0;
  wire w_TX_Active, w_UART_Line;
  wire w_TX_Serial;
  reg [7:0] r_TX_Byte = 0;
  wire [7:0] w_RX_Byte;

  UART_RX #(.CLKS_PER_BIT(c_CLKS_PER_BIT)) UART_RX_Inst
    (.i_Clock(r_Clock),
     .i_RX_Serial(w_UART_Line),
     .o_RX_DV(w_RX_DV),
     .o_RX_Byte(w_RX_Byte)
     );
  
  UART_TX #(.CLKS_PER_BIT(c_CLKS_PER_BIT)) UART_TX_Inst
    (.i_Clock(r_Clock),
     .i_TX_DV(r_TX_DV),
     .i_TX_Byte(r_TX_Byte),
     .o_TX_Active(w_TX_Active),
     .o_TX_Serial(w_TX_Serial),
     .o_TX_Done()
     );

  // Keeps the UART Receive input high (default) when
  // UART transmitter is not active
  assign w_UART_Line = w_TX_Active ? w_TX_Serial : 1'b1;
    
  always
    #(c_CLOCK_PERIOD_NS/2) r_Clock <= !r_Clock;
  
  // Main Testing:
  initial
    begin
      // Tell UART to send a command (exercise TX)
      @(posedge r_Clock);
      @(posedge r_Clock);
      r_TX_DV   <= 1'b1;
      r_TX_Byte <= 8'h3F;
      @(posedge r_Clock);
      r_TX_DV <= 1'b0;

      // Check that the correct command was received
      @(posedge w_RX_DV);
      if (w_RX_Byte == 8'h3F)
        $display("Test Passed - Correct Byte Received");
      else
        $display("Test Failed - Incorrect Byte Received");
      $finish();
    end
  
  initial 
    begin
      // Required to dump signals to EPWave
      $dumpfile("dump.vcd");
      $dumpvars(0);
    end
endmodule

05.UART/dump.vcd
$date
	Sat Mar 26 13:35:10 2022
$end
$version
	Icarus Verilog
$end
$timescale
	1ns
$end
$scope module UART_TB $end
$var wire 1 ! w_UART_Line $end
$var wire 1 " w_TX_Serial $end
$var wire 1 # w_TX_Active $end
$var wire 1 $ w_RX_DV $end
$var wire 8 % w_RX_Byte [7:0] $end
$var reg 1 & r_Clock $end
$var reg 8 ' r_TX_Byte [7:0] $end
$var reg 1 ( r_TX_DV $end
$scope module UART_RX_Inst $end
$var wire 1 & i_Clock $end
$var wire 1 ! i_RX_Serial $end
$var wire 1 ) i_Rst_L $end
$var reg 8 * o_RX_Byte [7:0] $end
$var reg 1 $ o_RX_DV $end
$var reg 3 + r_Bit_Index [2:0] $end
$var reg 8 , r_Clock_Count [7:0] $end
$var reg 3 - r_SM_Main [2:0] $end
$upscope $end
$scope module UART_TX_Inst $end
$var wire 1 & i_Clock $end
$var wire 1 . i_Rst_L $end
$var wire 8 / i_TX_Byte [7:0] $end
$var wire 1 ( i_TX_DV $end
$var reg 1 # o_TX_Active $end
$var reg 1 0 o_TX_Done $end
$var reg 1 " o_TX_Serial $end
$var reg 3 1 r_Bit_Index [2:0] $end
$var reg 9 2 r_Clock_Count [8:0] $end
$var reg 3 3 r_SM_Main [2:0] $end
$var reg 8 4 r_TX_Data [7:0] $end
$upscope $end
$upscope $end
$enddefinitions $end
#0
$dumpvars
bx 4
bx 3
bx 2
bx 1
x0
b0 /
z.
bx -
bx ,
bx +
bx *
z)
0(
b0 '
0&
bx %
x$
x#
x"
x!
$end
#200
b0 -
b0 3
1&
#400
0&
#600
1!
b0 +
b0 ,
0$
b0 1
b0 2
00
1"
b111111 '
b111111 /
1(
1&
#800
0&
#1000
b1 3
b111111 4
1#
0(
1&
#1200
0&
#1400
0!
b1 2
0"
1&
#1600
0&
#1800
b1 -
b10 2
1&
#2000
0&
#2200
b1 ,
b11 2
1&
#2400
0&
#2600
b10 ,
b100 2
1&
#2800
0&
#3000
b11 ,
b101 2
1&
#3200
0&
#3400
b100 ,
b110 2
1&
#3600
0&
#3800
b101 ,
b111 2
1&
#4000
0&
#4200
b110 ,
b1000 2
1&
#4400
0&
#4600
b111 ,
b1001 2
1&
#4800
0&
#5000
b1000 ,
b1010 2
1&
#5200
0&
#5400
b1001 ,
b1011 2
1&
#5600
0&
#5800
b1010 ,
b1100 2
1&
#6000
0&
#6200
b1011 ,
b1101 2
1&
#6400
0&
#6600
b1100 ,
b1110 2
1&
#6800
0&
#7000
b1101 ,
b1111 2
1&
#7200
0&
#7400
b1110 ,
b10000 2
1&
#7600
0&
#7800
b1111 ,
b10001 2
1&
#8000
0&
#8200
b10000 ,
b10010 2
1&
#8400
0&
#8600
b10001 ,
b10011 2
1&
#8800
0&
#9000
b10010 ,
b10100 2
1&
#9200
0&
#9400
b10011 ,
b10101 2
1&
#9600
0&
#9800
b10100 ,
b10110 2
1&
#10000
0&
#10200
b10101 ,
b10111 2
1&
#10400
0&
#10600
b10110 ,
b11000 2
1&
#10800
0&
#11000
b10111 ,
b11001 2
1&
#11200
0&
#11400
b11000 ,
b11010 2
1&
#11600
0&
#11800
b11001 ,
b11011 2
1&
#12000
0&
#12200
b11010 ,
b11100 2
1&
#12400
0&
#12600
b11011 ,
b11101 2
1&
#12800
0&
#13000
b11100 ,
b11110 2
1&
#13200
0&
#13400
b11101 ,
b11111 2
1&
#13600
0&
#13800
b11110 ,
b100000 2
1&
#14000
0&
#14200
b11111 ,
b100001 2
1&
#14400
0&
#14600
b100000 ,
b100010 2
1&
#14800
0&
#15000
b100001 ,
b100011 2
1&
#15200
0&
#15400
b100010 ,
b100100 2
1&
#15600
0&
#15800
b100011 ,
b100101 2
1&
#16000
0&
#16200
b100100 ,
b100110 2
1&
#16400
0&
#16600
b100101 ,
b100111 2
1&
#16800
0&
#17000
b100110 ,
b101000 2
1&
#17200
0&
#17400
b100111 ,
b101001 2
1&
#17600
0&
#17800
b101000 ,
b101010 2
1&
#18000
0&
#18200
b101001 ,
b101011 2
1&
#18400
0&
#18600
b101010 ,
b101100 2
1&
#18800
0&
#19000
b101011 ,
b101101 2
1&
#19200
0&
#19400
b101100 ,
b101110 2
1&
#19600
0&
#19800
b101101 ,
b101111 2
1&
#20000
0&
#20200
b101110 ,
b110000 2
1&
#20400
0&
#20600
b101111 ,
b110001 2
1&
#20800
0&
#21000
b110000 ,
b110010 2
1&
#21200
0&
#21400
b110001 ,
b110011 2
1&
#21600
0&
#21800
b110010 ,
b110100 2
1&
#22000
0&
#22200
b110011 ,
b110101 2
1&
#22400
0&
#22600
b110100 ,
b110110 2
1&
#22800
0&
#23000
b110101 ,
b110111 2
1&
#23200
0&
#23400
b110110 ,
b111000 2
1&
#23600
0&
#23800
b110111 ,
b111001 2
1&
#24000
0&
#24200
b111000 ,
b111010 2
1&
#24400
0&
#24600
b111001 ,
b111011 2
1&
#24800
0&
#25000
b111010 ,
b111100 2
1&
#25200
0&
#25400
b111011 ,
b111101 2
1&
#25600
0&
#25800
b111100 ,
b111110 2
1&
#26000
0&
#26200
b111101 ,
b111111 2
1&
#26400
0&
#26600
b111110 ,
b1000000 2
1&
#26800
0&
#27000
b111111 ,
b1000001 2
1&
#27200
0&
#27400
b1000000 ,
b1000010 2
1&
#27600
0&
#27800
b1000001 ,
b1000011 2
1&
#28000
0&
#28200
b1000010 ,
b1000100 2
1&
#28400
0&
#28600
b1000011 ,
b1000101 2
1&
#28800
0&
#29000
b1000100 ,
b1000110 2
1&
#29200
0&
#29400
b1000101 ,
b1000111 2
1&
#29600
0&
#29800
b1000110 ,
b1001000 2
1&
#30000
0&
#30200
b1000111 ,
b1001001 2
1&
#30400
0&
#30600
b1001000 ,
b1001010 2
1&
#30800
0&
#31000
b1001001 ,
b1001011 2
1&
#31200
0&
#31400
b1001010 ,
b1001100 2
1&
#31600
0&
#31800
b1001011 ,
b1001101 2
1&
#32000
0&
#32200
b1001100 ,
b1001110 2
1&
#32400
0&
#32600
b1001101 ,
b1001111 2
1&
#32800
0&
#33000
b1001110 ,
b1010000 2
1&
#33200
0&
#33400
b1001111 ,
b1010001 2
1&
#33600
0&
#33800
b1010000 ,
b1010010 2
1&
#34000
0&
#34200
b1010001 ,
b1010011 2
1&
#34400
0&
#34600
b1010010 ,
b1010100 2
1&
#34800
0&
#35000
b1010011 ,
b1010101 2
1&
#35200
0&
#35400
b1010100 ,
b1010110 2
1&
#35600
0&
#35800
b1010101 ,
b1010111 2
1&
#36000
0&
#36200
b1010110 ,
b1011000 2
1&
#36400
0&
#36600
b1010111 ,
b1011001 2
1&
#36800
0&
#37000
b1011000 ,
b1011010 2
1&
#37200
0&
#37400
b1011001 ,
b1011011 2
1&
#37600
0&
#37800
b1011010 ,
b1011100 2
1&
#38000
0&
#38200
b1011011 ,
b1011101 2
1&
#38400
0&
#38600
b1011100 ,
b1011110 2
1&
#38800
0&
#39000
b1011101 ,
b1011111 2
1&
#39200
0&
#39400
b1011110 ,
b1100000 2
1&
#39600
0&
#39800
b1011111 ,
b1100001 2
1&
#40000
0&
#40200
b1100000 ,
b1100010 2
1&
#40400
0&
#40600
b1100001 ,
b1100011 2
1&
#40800
0&
#41000
b1100010 ,
b1100100 2
1&
#41200
0&
#41400
b1100011 ,
b1100101 2
1&
#41600
0&
#41800
b1100100 ,
b1100110 2
1&
#42000
0&
#42200
b1100101 ,
b1100111 2
1&
#42400
0&
#42600
b1100110 ,
b1101000 2
1&
#42800
0&
#43000
b1100111 ,
b1101001 2
1&
#43200
0&
#43400
b1101000 ,
b1101010 2
1&
#43600
0&
#43800
b1101001 ,
b1101011 2
1&
#44000
0&
#44200
b1101010 ,
b1101100 2
1&
#44400
0&
#44600
b1101011 ,
b1101101 2
1&
#44800
0&
#45000
b1101100 ,
b1101110 2
1&
#45200
0&
#45400
b10 -
b0 ,
b1101111 2
1&
#45600
0&
#45800
b1 ,
b1110000 2
1&
#46000
0&
#46200
b10 ,
b1110001 2
1&
#46400
0&
#46600
b11 ,
b1110010 2
1&
#46800
0&
#47000
b100 ,
b1110011 2
1&
#47200
0&
#47400
b101 ,
b1110100 2
1&
#47600
0&
#47800
b110 ,
b1110101 2
1&
#48000
0&
#48200
b111 ,
b1110110 2
1&
#48400
0&
#48600
b1000 ,
b1110111 2
1&
#48800
0&
#49000
b1001 ,
b1111000 2
1&
#49200
0&
#49400
b1010 ,
b1111001 2
1&
#49600
0&
#49800
b1011 ,
b1111010 2
1&
#50000
0&
#50200
b1100 ,
b1111011 2
1&
#50400
0&
#50600
b1101 ,
b1111100 2
1&
#50800
0&
#51000
b1110 ,
b1111101 2
1&
#51200
0&
#51400
b1111 ,
b1111110 2
1&
#51600
0&
#51800
b10000 ,
b1111111 2
1&
#52000
0&
#52200
b10001 ,
b10000000 2
1&
#52400
0&
#52600
b10010 ,
b10000001 2
1&
#52800
0&
#53000
b10011 ,
b10000010 2
1&
#53200
0&
#53400
b10100 ,
b10000011 2
1&
#53600
0&
#53800
b10101 ,
b10000100 2
1&
#54000
0&
#54200
b10110 ,
b10000101 2
1&
#54400
0&
#54600
b10111 ,
b10000110 2
1&
#54800
0&
#55000
b11000 ,
b10000111 2
1&
#55200
0&
#55400
b11001 ,
b10001000 2
1&
#55600
0&
#55800
b11010 ,
b10001001 2
1&
#56000
0&
#56200
b11011 ,
b10001010 2
1&
#56400
0&
#56600
b11100 ,
b10001011 2
1&
#56800
0&
#57000
b11101 ,
b10001100 2
1&
#57200
0&
#57400
b11110 ,
b10001101 2
1&
#57600
0&
#57800
b11111 ,
b10001110 2
1&
#58000
0&
#58200
b100000 ,
b10001111 2
1&
#58400
0&
#58600
b100001 ,
b10010000 2
1&
#58800
0&
#59000
b100010 ,
b10010001 2
1&
#59200
0&
#59400
b100011 ,
b10010010 2
1&
#59600
0&
#59800
b100100 ,
b10010011 2
1&
#60000
0&
#60200
b100101 ,
b10010100 2
1&
#60400
0&
#60600
b100110 ,
b10010101 2
1&
#60800
0&
#61000
b100111 ,
b10010110 2
1&
#61200
0&
#61400
b101000 ,
b10010111 2
1&
#61600
0&
#61800
b101001 ,
b10011000 2
1&
#62000
0&
#62200
b101010 ,
b10011001 2
1&
#62400
0&
#62600
b101011 ,
b10011010 2
1&
#62800
0&
#63000
b101100 ,
b10011011 2
1&
#63200
0&
#63400
b101101 ,
b10011100 2
1&
#63600
0&
#63800
b101110 ,
b10011101 2
1&
#64000
0&
#64200
b101111 ,
b10011110 2
1&
#64400
0&
#64600
b110000 ,
b10011111 2
1&
#64800
0&
#65000
b110001 ,
b10100000 2
1&
#65200
0&
#65400
b110010 ,
b10100001 2
1&
#65600
0&
#65800
b110011 ,
b10100010 2
1&
#66000
0&
#66200
b110100 ,
b10100011 2
1&
#66400
0&
#66600
b110101 ,
b10100100 2
1&
#66800
0&
#67000
b110110 ,
b10100101 2
1&
#67200
0&
#67400
b110111 ,
b10100110 2
1&
#67600
0&
#67800
b111000 ,
b10100111 2
1&
#68000
0&
#68200
b111001 ,
b10101000 2
1&
#68400
0&
#68600
b111010 ,
b10101001 2
1&
#68800
0&
#69000
b111011 ,
b10101010 2
1&
#69200
0&
#69400
b111100 ,
b10101011 2
1&
#69600
0&
#69800
b111101 ,
b10101100 2
1&
#70000
0&
#70200
b111110 ,
b10101101 2
1&
#70400
0&
#70600
b111111 ,
b10101110 2
1&
#70800
0&
#71000
b1000000 ,
b10101111 2
1&
#71200
0&
#71400
b1000001 ,
b10110000 2
1&
#71600
0&
#71800
b1000010 ,
b10110001 2
1&
#72000
0&
#72200
b1000011 ,
b10110010 2
1&
#72400
0&
#72600
b1000100 ,
b10110011 2
1&
#72800
0&
#73000
b1000101 ,
b10110100 2
1&
#73200
0&
#73400
b1000110 ,
b10110101 2
1&
#73600
0&
#73800
b1000111 ,
b10110110 2
1&
#74000
0&
#74200
b1001000 ,
b10110111 2
1&
#74400
0&
#74600
b1001001 ,
b10111000 2
1&
#74800
0&
#75000
b1001010 ,
b10111001 2
1&
#75200
0&
#75400
b1001011 ,
b10111010 2
1&
#75600
0&
#75800
b1001100 ,
b10111011 2
1&
#76000
0&
#76200
b1001101 ,
b10111100 2
1&
#76400
0&
#76600
b1001110 ,
b10111101 2
1&
#76800
0&
#77000
b1001111 ,
b10111110 2
1&
#77200
0&
#77400
b1010000 ,
b10111111 2
1&
#77600
0&
#77800
b1010001 ,
b11000000 2
1&
#78000
0&
#78200
b1010010 ,
b11000001 2
1&
#78400
0&
#78600
b1010011 ,
b11000010 2
1&
#78800
0&
#79000
b1010100 ,
b11000011 2
1&
#79200
0&
#79400
b1010101 ,
b11000100 2
1&
#79600
0&
#79800
b1010110 ,
b11000101 2
1&
#80000
0&
#80200
b1010111 ,
b11000110 2
1&
#80400
0&
#80600
b1011000 ,
b11000111 2
1&
#80800
0&
#81000
b1011001 ,
b11001000 2
1&
#81200
0&
#81400
b1011010 ,
b11001001 2
1&
#81600
0&
#81800
b1011011 ,
b11001010 2
1&
#82000
0&
#82200
b1011100 ,
b11001011 2
1&
#82400
0&
#82600
b1011101 ,
b11001100 2
1&
#82800
0&
#83000
b1011110 ,
b11001101 2
1&
#83200
0&
#83400
b1011111 ,
b11001110 2
1&
#83600
0&
#83800
b1100000 ,
b11001111 2
1&
#84000
0&
#84200
b1100001 ,
b11010000 2
1&
#84400
0&
#84600
b1100010 ,
b11010001 2
1&
#84800
0&
#85000
b1100011 ,
b11010010 2
1&
#85200
0&
#85400
b1100100 ,
b11010011 2
1&
#85600
0&
#85800
b1100101 ,
b11010100 2
1&
#86000
0&
#86200
b1100110 ,
b11010101 2
1&
#86400
0&
#86600
b1100111 ,
b11010110 2
1&
#86800
0&
#87000
b1101000 ,
b11010111 2
1&
#87200
0&
#87400
b1101001 ,
b11011000 2
1&
#87600
0&
#87800
b1101010 ,
b10 3
b0 2
1&
#88000
0&
#88200
1!
b1101011 ,
b1 2
1"
1&
#88400
0&
#88600
b1101100 ,
b10 2
1&
#88800
0&
#89000
b1101101 ,
b11 2
1&
#89200
0&
#89400
b1101110 ,
b100 2
1&
#89600
0&
#89800
b1101111 ,
b101 2
1&
#90000
0&
#90200
b1110000 ,
b110 2
1&
#90400
0&
#90600
b1110001 ,
b111 2
1&
#90800
0&
#91000
b1110010 ,
b1000 2
1&
#91200
0&
#91400
b1110011 ,
b1001 2
1&
#91600
0&
#91800
b1110100 ,
b1010 2
1&
#92000
0&
#92200
b1110101 ,
b1011 2
1&
#92400
0&
#92600
b1110110 ,
b1100 2
1&
#92800
0&
#93000
b1110111 ,
b1101 2
1&
#93200
0&
#93400
b1111000 ,
b1110 2
1&
#93600
0&
#93800
b1111001 ,
b1111 2
1&
#94000
0&
#94200
b1111010 ,
b10000 2
1&
#94400
0&
#94600
b1111011 ,
b10001 2
1&
#94800
0&
#95000
b1111100 ,
b10010 2
1&
#95200
0&
#95400
b1111101 ,
b10011 2
1&
#95600
0&
#95800
b1111110 ,
b10100 2
1&
#96000
0&
#96200
b1111111 ,
b10101 2
1&
#96400
0&
#96600
b10000000 ,
b10110 2
1&
#96800
0&
#97000
b10000001 ,
b10111 2
1&
#97200
0&
#97400
b10000010 ,
b11000 2
1&
#97600
0&
#97800
b10000011 ,
b11001 2
1&
#98000
0&
#98200
b10000100 ,
b11010 2
1&
#98400
0&
#98600
b10000101 ,
b11011 2
1&
#98800
0&
#99000
b10000110 ,
b11100 2
1&
#99200
0&
#99400
b10000111 ,
b11101 2
1&
#99600
0&
#99800
b10001000 ,
b11110 2
1&
#100000
0&
#100200
b10001001 ,
b11111 2
1&
#100400
0&
#100600
b10001010 ,
b100000 2
1&
#100800
0&
#101000
b10001011 ,
b100001 2
1&
#101200
0&
#101400
b10001100 ,
b100010 2
1&
#101600
0&
#101800
b10001101 ,
b100011 2
1&
#102000
0&
#102200
b10001110 ,
b100100 2
1&
#102400
0&
#102600
b10001111 ,
b100101 2
1&
#102800
0&
#103000
b10010000 ,
b100110 2
1&
#103200
0&
#103400
b10010001 ,
b100111 2
1&
#103600
0&
#103800
b10010010 ,
b101000 2
1&
#104000
0&
#104200
b10010011 ,
b101001 2
1&
#104400
0&
#104600
b10010100 ,
b101010 2
1&
#104800
0&
#105000
b10010101 ,
b101011 2
1&
#105200
0&
#105400
b10010110 ,
b101100 2
1&
#105600
0&
#105800
b10010111 ,
b101101 2
1&
#106000
0&
#106200
b10011000 ,
b101110 2
1&
#106400
0&
#106600
b10011001 ,
b101111 2
1&
#106800
0&
#107000
b10011010 ,
b110000 2
1&
#107200
0&
#107400
b10011011 ,
b110001 2
1&
#107600
0&
#107800
b10011100 ,
b110010 2
1&
#108000
0&
#108200
b10011101 ,
b110011 2
1&
#108400
0&
#108600
b10011110 ,
b110100 2
1&
#108800
0&
#109000
b10011111 ,
b110101 2
1&
#109200
0&
#109400
b10100000 ,
b110110 2
1&
#109600
0&
#109800
b10100001 ,
b110111 2
1&
#110000
0&
#110200
b10100010 ,
b111000 2
1&
#110400
0&
#110600
b10100011 ,
b111001 2
1&
#110800
0&
#111000
b10100100 ,
b111010 2
1&
#111200
0&
#111400
b10100101 ,
b111011 2
1&
#111600
0&
#111800
b10100110 ,
b111100 2
1&
#112000
0&
#112200
b10100111 ,
b111101 2
1&
#112400
0&
#112600
b10101000 ,
b111110 2
1&
#112800
0&
#113000
b10101001 ,
b111111 2
1&
#113200
0&
#113400
b10101010 ,
b1000000 2
1&
#113600
0&
#113800
b10101011 ,
b1000001 2
1&
#114000
0&
#114200
b10101100 ,
b1000010 2
1&
#114400
0&
#114600
b10101101 ,
b1000011 2
1&
#114800
0&
#115000
b10101110 ,
b1000100 2
1&
#115200
0&
#115400
b10101111 ,
b1000101 2
1&
#115600
0&
#115800
b10110000 ,
b1000110 2
1&
#116000
0&
#116200
b10110001 ,
b1000111 2
1&
#116400
0&
#116600
b10110010 ,
b1001000 2
1&
#116800
0&
#117000
b10110011 ,
b1001001 2
1&
#117200
0&
#117400
b10110100 ,
b1001010 2
1&
#117600
0&
#117800
b10110101 ,
b1001011 2
1&
#118000
0&
#118200
b10110110 ,
b1001100 2
1&
#118400
0&
#118600
b10110111 ,
b1001101 2
1&
#118800
0&
#119000
b10111000 ,
b1001110 2
1&
#119200
0&
#119400
b10111001 ,
b1001111 2
1&
#119600
0&
#119800
b10111010 ,
b1010000 2
1&
#120000
0&
#120200
b10111011 ,
b1010001 2
1&
#120400
0&
#120600
b10111100 ,
b1010010 2
1&
#120800
0&
#121000
b10111101 ,
b1010011 2
1&
#121200
0&
#121400
b10111110 ,
b1010100 2
1&
#121600
0&
#121800
b10111111 ,
b1010101 2
1&
#122000
0&
#122200
b11000000 ,
b1010110 2
1&
#122400
0&
#122600
b11000001 ,
b1010111 2
1&
#122800
0&
#123000
b11000010 ,
b1011000 2
1&
#123200
0&
#123400
b11000011 ,
b1011001 2
1&
#123600
0&
#123800
b11000100 ,
b1011010 2
1&
#124000
0&
#124200
b11000101 ,
b1011011 2
1&
#124400
0&
#124600
b11000110 ,
b1011100 2
1&
#124800
0&
#125000
b11000111 ,
b1011101 2
1&
#125200
0&
#125400
b11001000 ,
b1011110 2
1&
#125600
0&
#125800
b11001001 ,
b1011111 2
1&
#126000
0&
#126200
b11001010 ,
b1100000 2
1&
#126400
0&
#126600
b11001011 ,
b1100001 2
1&
#126800
0&
#127000
b11001100 ,
b1100010 2
1&
#127200
0&
#127400
b11001101 ,
b1100011 2
1&
#127600
0&
#127800
b11001110 ,
b1100100 2
1&
#128000
0&
#128200
b11001111 ,
b1100101 2
1&
#128400
0&
#128600
b11010000 ,
b1100110 2
1&
#128800
0&
#129000
b11010001 ,
b1100111 2
1&
#129200
0&
#129400
b11010010 ,
b1101000 2
1&
#129600
0&
#129800
b11010011 ,
b1101001 2
1&
#130000
0&
#130200
b11010100 ,
b1101010 2
1&
#130400
0&
#130600
b11010101 ,
b1101011 2
1&
#130800
0&
#131000
b11010110 ,
b1101100 2
1&
#131200
0&
#131400
b11010111 ,
b1101101 2
1&
#131600
0&
#131800
b11011000 ,
b1101110 2
1&
#132000
0&
#132200
b1 +
bx1 %
bx1 *
b0 ,
b1101111 2
1&
#132400
0&
#132600
b1 ,
b1110000 2
1&
#132800
0&
#133000
b10 ,
b1110001 2
1&
#133200
0&
#133400
b11 ,
b1110010 2
1&
#133600
0&
