02.multiplexer/02.ternary operator/multiplexer.v
// 4 in 1 multiplexer
module multiplexer (
    input i0, i1, i2, i3,
    output out,
    input s0, s1
);

assign out = s1 ? (s0 ? i3 : i2) : (s0 ? i1 : i0);

endmodule

02.multiplexer/02.ternary operator/mux_tb.v
module top;

reg i0, i1, i2, i3;
wire out;
reg s0, s1;

multiplexer m1(.i0(i0), .i1(i1), .i2(i2), .i3(i3), .out(out), .s0(s0), .s1(s1));

initial begin
    $dumpfile("muxgen.vcd");
    $dumpvars(0, m1);
end

initial begin
    s0 = 0; s1 = 0; i0 = 1; i1 = 0; i2 = 0; i3 = 0;
    $monitor($time, " s0 = %b, s1 = %b, OUT = %b", s0, s1, out);
    #1
    s0 = 1; s1 = 0;
    #1
    i0 = 0; i1 = 1;
    #1
    s0 = 0; s1 = 1;
    #1
    i1 = 0; i2 = 1;
    #1
    s0 = 1; s1 = 1;
    #1
    i2 = 0; i3 = 1;
    #1
    s0 = 0; s1 = 0;
    #1
    i3 = 0; i1 = 1;

end

endmodule

02.multiplexer/02.ternary operator/muxgen.vcd
$date
	Sat Dec 18 16:49:32 2021
$end
$version
	Icarus Verilog
$end
$timescale
	1s
$end
$scope module top $end
$scope module m1 $end
$var wire 1 ! i0 $end
$var wire 1 " i1 $end
$var wire 1 # i2 $end
$var wire 1 $ i3 $end
$var wire 1 % s0 $end
$var wire 1 & s1 $end
$var wire 1 ' out $end
$upscope $end
$upscope $end
$enddefinitions $end
#0
$dumpvars
1'
0&
0%
0$
0#
0"
1!
$end
#1
0'
1%
#2
1'
1"
0!
#3
0'
1&
0%
#4
1'
1#
0"
#5
0'
1%
#6
1'
1$
0#
#7
0'
0&
0%
#8
1"
0$
