00.RippleCarryCounter/01.gate level/D_FF.v
module D_FF (
    output q, qbar,
    input d,
    input clk,
    input reset
);

wire cbar, s, sbar, r, rbar;

assign cbar = ~reset; // reset = clear

assign sbar = ~(rbar & s);
assign s = ~(sbar & ~clk & cbar);
assign r = ~(s & ~clk & rbar);
assign rbar = ~(r & cbar & d);

assign q = ~(s & qbar);
assign qbar = ~(q & cbar & r);
    
endmodule

00.RippleCarryCounter/01.gate level/T_FF.v
module T_FF (
    output q,
    input clk,
    input reset
);


D_FF dff0(.q(q), .d(~q), .clk(clk), .reset(reset));
//qbar isn't connected.

endmodule

00.RippleCarryCounter/01.gate level/ripple_carry_counter.v
module ripple_carry_counter(
    output [3:0] q,
    input clk,
    input reset
);

T_FF tff0(.q(q[0]),.clk(clk),.reset(reset));
T_FF tff1(.q(q[1]),.clk(q[0]),.reset(reset));
T_FF tff2(.q(q[2]),.clk(q[1]),.reset(reset));
T_FF tff3(.q(q[3]),.clk(q[2]),.reset(reset));

endmodule

00.test/RCC_tb.v
module stimulus;

reg clk;
reg reset;
wire [3:0] q;

ripple_carry_counter r1 (.q(q), .clk(clk), .reset(reset));

initial begin
    clk = 1'b0;
    $dumpfile("dump.vcd");
    $dumpvars(0, r1);
end
always
    #5 clk = ~clk;


initial begin
    reset = 1'b1;
    #15 reset = 1'b0;
    #180 reset = 1'b1;
    #10 reset = 1'b0;
    #20 $finish;
end

initial 
    $monitor($time, " output q = %d", q);


endmodule

00.RippleCarryCounter/01.gate level/dump.vcd
$date
	Sat Dec 18 17:21:14 2021
$end
$version
	Icarus Verilog
$end
$timescale
	1s
$end
$scope module stimulus $end
$scope module r1 $end
$var wire 1 ! clk $end
$var wire 1 " reset $end
$var wire 4 # q [3:0] $end
$scope module tff0 $end
$var wire 1 ! clk $end
$var wire 1 " reset $end
$var wire 1 $ q $end
$scope module dff0 $end
$var wire 1 % cbar $end
$var wire 1 ! clk $end
$var wire 1 & d $end
$var wire 1 $ q $end
$var wire 1 ' qbar $end
$var wire 1 ( r $end
$var wire 1 ) rbar $end
$var wire 1 " reset $end
$var wire 1 * s $end
$var wire 1 + sbar $end
$upscope $end
$upscope $end
$scope module tff1 $end
$var wire 1 , clk $end
$var wire 1 " reset $end
$var wire 1 - q $end
$scope module dff0 $end
$var wire 1 . cbar $end
$var wire 1 , clk $end
$var wire 1 / d $end
$var wire 1 - q $end
$var wire 1 0 qbar $end
$var wire 1 1 r $end
$var wire 1 2 rbar $end
$var wire 1 " reset $end
$var wire 1 3 s $end
$var wire 1 4 sbar $end
$upscope $end
$upscope $end
$scope module tff2 $end
$var wire 1 5 clk $end
$var wire 1 " reset $end
$var wire 1 6 q $end
$scope module dff0 $end
$var wire 1 7 cbar $end
$var wire 1 5 clk $end
$var wire 1 8 d $end
$var wire 1 6 q $end
$var wire 1 9 qbar $end
$var wire 1 : r $end
$var wire 1 ; rbar $end
$var wire 1 " reset $end
$var wire 1 < s $end
$var wire 1 = sbar $end
$upscope $end
$upscope $end
$scope module tff3 $end
$var wire 1 > clk $end
$var wire 1 " reset $end
$var wire 1 ? q $end
$scope module dff0 $end
$var wire 1 @ cbar $end
$var wire 1 > clk $end
$var wire 1 A d $end
$var wire 1 ? q $end
$var wire 1 B qbar $end
$var wire 1 C r $end
$var wire 1 D rbar $end
$var wire 1 " reset $end
$var wire 1 E s $end
$var wire 1 F sbar $end
$upscope $end
$upscope $end
$upscope $end
$upscope $end
$enddefinitions $end
#0
$dumpvars
0F
1E
1D
0C
1B
1A
0@
0?
0>
0=
1<
1;
0:
19
18
07
06
05
04
13
12
01
10
1/
0.
0-
0,
0+
1*
1)
0(
1'
1&
0%
0$
b0 #
1"
0!
$end
#5
1(
1!
#10
0(
0!
#15
1+
0)
1(
1%
1.
17
1@
1!
0"
#20
14
02
11
0'
1)
0&
1,
b1 #
1$
0*
0!
#25
0+
1*
1!
#30
1=
0;
1:
00
12
0/
15
1-
03
1&
0,
b10 #
0$
1'
0(
0!
#35
1+
0)
1(
1!
#40
04
13
0'
1)
0&
1,
b11 #
1$
0*
0!
#45
0+
1*
1!
#50
1F
0D
1C
09
1;
08
1>
16
0<
1/
05
0-
10
01
1&
0,
b100 #
0$
1'
0(
0!
#55
1+
0)
1(
1!
#60
14
02
11
0'
1)
0&
1,
b101 #
1$
0*
0!
#65
0+
1*
1!
#70
0=
1<
00
12
0/
15
1-
03
1&
0,
b110 #
0$
1'
0(
0!
#75
1+
0)
1(
1!
#80
04
13
0'
1)
0&
1,
b111 #
1$
0*
0!
#85
0+
1*
1!
#90
0B
1D
0A
1?
0E
18
0>
06
19
0:
1/
05
0-
10
01
1&
0,
b1000 #
0$
1'
0(
0!
#95
1+
0)
1(
1!
#100
14
02
11
0'
1)
0&
1,
b1001 #
1$
0*
0!
#105
0+
1*
1!
#110
1=
0;
1:
00
12
0/
15
1-
03
1&
0,
b1010 #
0$
1'
0(
0!
#115
1+
0)
1(
1!
#120
04
13
0'
1)
0&
1,
b1011 #
1$
0*
0!
#125
0+
1*
1!
#130
0F
1E
09
1;
08
1>
16
0<
1/
05
0-
10
01
1&
0,
b1100 #
0$
1'
0(
0!
#135
1+
0)
1(
1!
#140
14
02
11
0'
1)
0&
1,
b1101 #
1$
0*
0!
#145
0+
1*
1!
#150
0=
1<
00
12
0/
15
1-
03
1&
0,
b1110 #
0$
1'
0(
0!
#155
1+
0)
1(
1!
#160
04
13
0'
1)
0&
1,
b1111 #
1$
0*
0!
#165
0+
1*
1!
#170
1A
0?
1B
0C
18
0>
06
19
0:
1/
05
0-
10
01
1&
0,
b0 #
0$
1'
0(
0!
#175
1+
0)
1(
1!
#180
14
02
11
0'
1)
0&
1,
b1 #
1$
0*
0!
#185
0+
1*
1!
#190
1=
0;
1:
00
12
0/
15
1-
03
1&
0,
b10 #
0$
1'
0(
0!
#195
0:
01
1/
05
0=
b0 #
0-
04
1(
10
1;
13
0%
0.
07
0@
1!
1"
#200
0(
0!
#205
1+
0)
1(
1%
1.
17
1@
1!
0"
#210
14
02
11
0'
1)
0&
1,
b1 #
1$
0*
0!
#215
0+
1*
1!
#220
1=
0;
1:
00
12
0/
15
1-
03
1&
0,
b10 #
0$
1'
0(
0!
#225
1+
0)
1(
1!
