00.test/D_FF.v
module D_FF (
    output reg q,
    input d,
    input clk,
    input reset
);

always @(posedge reset or negedge clk) begin
    if (reset)
        q <= 1'b0;
    else
        q <= d;
end
    
endmodule

00.RippleCarryCounter/01.gate level/T_FF.v
module T_FF (
    output q,
    input clk,
    input reset
);


D_FF dff0(.q(q), .d(~q), .clk(clk), .reset(reset));
//qbar isn't connected.

endmodule

00.RippleCarryCounter/01.gate level/ripple_carry_counter.v
module ripple_carry_counter(
    output [3:0] q,
    input clk,
    input reset
);

T_FF tff0(.q(q[0]),.clk(clk),.reset(reset));
T_FF tff1(.q(q[1]),.clk(q[0]),.reset(reset));
T_FF tff2(.q(q[2]),.clk(q[1]),.reset(reset));
T_FF tff3(.q(q[3]),.clk(q[2]),.reset(reset));

endmodule

00.test/RCC_tb.v
module stimulus;

reg clk;
reg reset;
wire [3:0] q;

ripple_carry_counter r1 (.q(q), .clk(clk), .reset(reset));

initial begin
    clk = 1'b0;
    $dumpfile("dump.vcd");
    $dumpvars(0, r1);
end
always
    #5 clk = ~clk;


initial begin
    reset = 1'b1;
    #15 reset = 1'b0;
    #180 reset = 1'b1;
    #10 reset = 1'b0;
    #20 $finish;
end

initial 
    $monitor($time, " output q = %d", q);


endmodule

00.test/dump.vcd
$date
	Wed Dec 15 23:25:15 2021
$end
$version
	Icarus Verilog
$end
$timescale
	1s
$end
$scope module stimulus $end
$scope module r1 $end
$var wire 1 ! clk $end
$var wire 1 " reset $end
$var wire 4 # q [3:0] $end
$scope module tff0 $end
$var wire 1 ! clk $end
$var wire 1 $ d $end
$var wire 1 " reset $end
$var wire 1 % q $end
$scope module dff0 $end
$var wire 1 ! clk $end
$var wire 1 $ d $end
$var wire 1 " reset $end
$var reg 1 % q $end
$upscope $end
$upscope $end
$scope module tff1 $end
$var wire 1 & clk $end
$var wire 1 ' d $end
$var wire 1 " reset $end
$var wire 1 ( q $end
$scope module dff0 $end
$var wire 1 & clk $end
$var wire 1 ' d $end
$var wire 1 " reset $end
$var reg 1 ( q $end
$upscope $end
$upscope $end
$scope module tff2 $end
$var wire 1 ) clk $end
$var wire 1 * d $end
$var wire 1 " reset $end
$var wire 1 + q $end
$scope module dff0 $end
$var wire 1 ) clk $end
$var wire 1 * d $end
$var wire 1 " reset $end
$var reg 1 + q $end
$upscope $end
$upscope $end
$scope module tff3 $end
$var wire 1 , clk $end
$var wire 1 - d $end
$var wire 1 " reset $end
$var wire 1 . q $end
$scope module dff0 $end
$var wire 1 , clk $end
$var wire 1 - d $end
$var wire 1 " reset $end
$var reg 1 . q $end
$upscope $end
$upscope $end
$upscope $end
$upscope $end
$enddefinitions $end
#0
$dumpvars
0.
1-
0,
0+
1*
0)
0(
1'
0&
0%
1$
b0 #
1"
0!
$end
#5
1!
#10
0!
#15
1!
0"
#20
0$
1&
b1 #
1%
0!
#25
1!
#30
0'
1)
1(
1$
0&
b10 #
0%
0!
#35
1!
#40
0$
1&
b11 #
1%
0!
#45
1!
#50
0*
1,
1+
1'
0)
0(
1$
0&
b100 #
0%
0!
#55
1!
#60
0$
1&
b101 #
1%
0!
#65
1!
#70
0'
1)
1(
1$
0&
b110 #
0%
0!
#75
1!
#80
0$
1&
b111 #
1%
0!
#85
1!
#90
0-
1.
1*
0,
0+
1'
0)
0(
1$
0&
b1000 #
0%
0!
#95
1!
#100
0$
1&
b1001 #
1%
0!
#105
1!
#110
0'
1)
1(
1$
0&
b1010 #
0%
0!
#115
1!
#120
0$
1&
b1011 #
1%
0!
#125
1!
#130
0*
1,
1+
1'
0)
0(
1$
0&
b1100 #
0%
0!
#135
1!
#140
0$
1&
b1101 #
1%
0!
#145
1!
#150
0'
1)
1(
1$
0&
b1110 #
0%
0!
#155
1!
#160
0$
1&
b1111 #
1%
0!
#165
1!
#170
1-
0.
1*
0,
0+
1'
0)
0(
1$
0&
b0 #
0%
0!
#175
1!
#180
0$
1&
b1 #
1%
0!
#185
1!
#190
0'
1)
1(
1$
0&
b10 #
0%
0!
#195
1'
0)
b0 #
0(
1!
1"
#200
0!
#205
1!
0"
#210
0$
1&
b1 #
1%
0!
#215
1!
#220
0'
1)
1(
1$
0&
b10 #
0%
0!
